cli.py
env_checker/__init__.py
env_checker/core.py
envconfig_checker-0.1.1.dist-info/LICENSE
envconfig_checker-0.1.1.dist-info/METADATA
envconfig_checker-0.1.1.dist-info/WHEEL
envconfig_checker-0.1.1.dist-info/entry_points.txt
envconfig_checker-0.1.1.dist-info/top_level.txt
envconfig_checker-0.1.1.dist-info/RECORD
